delete_branches/__init__.py
delete_branches/__main__.py
delete_branches/run.py
delete_branches-1.2.15.dist-info/licenses/LICENSE
delete_branches-1.2.15.dist-info/METADATA
delete_branches-1.2.15.dist-info/WHEEL
delete_branches-1.2.15.dist-info/entry_points.txt
delete_branches-1.2.15.dist-info/top_level.txt
delete_branches-1.2.15.dist-info/RECORD
